Metadata-Version: 1.0
Name: nonsensepy
Version: 0.0.1
Summary: Generates random strings
Home-page: https://github.com/monzita/nonsensepy
Author: Monika Ilieva
Author-email: example@hidden.com
License: MIT License
Keywords: nonsensepy generator string random
Platform: UNKNOWN
